ormy/__init__.py
ormy/__version__.py
ormy/_abc/__init__.py
ormy/_abc/abstract.py
ormy/_abc/config.py
ormy/_abc/registry.py
ormy/base/__init__.py
ormy/base/decorator.py
ormy/base/func.py
ormy/base/generic.py
ormy/base/logging.py
ormy/base/pydantic.py
ormy/base/typing.py
ormy/document/__init__.py
ormy/document/_abc.py
ormy/document/arango/__init__.py
ormy/document/arango/builder.py
ormy/document/arango/config.py
ormy/document/arango/wrapper.py
ormy/document/firestore/__init__.py
ormy/document/firestore/config.py
ormy/document/firestore/wrapper.py
ormy/document/mixin/__init__.py
ormy/document/mixin/boilerplate.py
ormy/document/mixin/meilisearch/__init__.py
ormy/document/mixin/meilisearch/config.py
ormy/document/mixin/meilisearch/schema.py
ormy/document/mixin/meilisearch/wrapper.py
ormy/document/mixin/rabbitmq/__init__.py
ormy/document/mixin/rabbitmq/config.py
ormy/document/mixin/rabbitmq/wrapper.py
ormy/document/mixin/redlock/__init__.py
ormy/document/mixin/redlock/config.py
ormy/document/mixin/redlock/wrapper.py
ormy/document/mixin/s3/__init__.py
ormy/document/mixin/s3/config.py
ormy/document/mixin/s3/schema.py
ormy/document/mixin/s3/wrapper.py
ormy/document/mongo/__init__.py
ormy/document/mongo/config.py
ormy/document/mongo/wrapper.py
ormy/document/redis/__init__.py
ormy/document/redis/config.py
ormy/document/redis/wrapper.py
ormy/exceptions.py
ormy/py.typed
ormy/table/__init__.py
ormy/table/_abc.py
ormy/table/bigquery/__init__.py
ormy/table/bigquery/config.py
ormy/table/bigquery/exceptions.py
ormy/table/bigquery/wrapper.py
ormy/table/clickhouse/__init__.py
ormy/table/clickhouse/config.py
ormy/table/clickhouse/database.py
ormy/table/clickhouse/func.py
ormy/table/clickhouse/migrations.py
ormy/table/clickhouse/models.py
ormy/table/clickhouse/wrapper.py
ormy/utils/__init__.py
ormy/utils/auth/__init__.py
ormy/utils/auth/firebase.py
ormy/utils/auth/func.py
ormy/utils/auth/generic.py
ormy/utils/io.py
ormy/utils/misc/__init__.py
ormy/utils/misc/aiocache.py
ormy-0.1.46.dist-info/LICENSE
ormy-0.1.46.dist-info/METADATA
ormy-0.1.46.dist-info/WHEEL
ormy-0.1.46.dist-info/RECORD
